Workbook
Name L_YN: '选项'!$A$1:$A$2
Name L_DIR: '选项'!$B$1:$B$3
Name L_OP: '选项'!$C$1:$C$3
Name L_CONF: '选项'!$D$1:$D$4
Name L_BASIS: '选项'!$E$1:$E$33

Sheet 说明
B2: 业务语义数据登记表（初稿·树形）
B3: 由《全省农商行2026年7月主要经营指标一览表》和《61家归因分析_202606》自动整理，需业务方确认。生成日期 2026-10-09。
B5: 怎么看这棵树
B6: 板块 | C6: 深蓝色整行，如“二、存款”。每个板块下是该板块的指标。
B7: 指标 | C7: 缩进越深，层级越低；点左侧“+/-”可以展开、收起下级。
B8: 〔拆解方式〕 | C8: 指标下面的分组，如〔按担保方式〕。同一个指标可以有多种拆法，每种拆法单独一组；“自动校验”列显示该组下级加起来是否等于上级。
B9: 比率 | C9: 灰色，挂在它的分子指标下面，如“个人存款占比”挂在“个人存款”下。
B10: ↪ 引用 | C10: 灰色斜体。该指标同时属于多个上级，完整的下级只在一处展开，其他地方以引用出现，备注里写了展开位置。
B12: 请业务方做的三件事
B13: ① 定默认口径 | C13: 在下方黄色单元格中选择：用户没说口径时默认用哪个（全局只定一次）。
B14: ② 核对树的结构 | C14: 上下级、拆解方式、加/减/其中是否正确；“自动校验”出现 ✗ 的组请在备注中说明原因。需要新增节点时插入一行，并填写最右侧的“上级指标”“拆解方式”。
B15: ③ 核对目录对应 | C15: 每个指标在“业务确认”列下拉选择：正确 / 有误（备注写正确指标）/ 目录中没有 / 不需要。顺带确认黄色建议列。
B17: 全局设置
B18: 默认口径（必填）
B20: 整理情况（自动统计）
B21: 指标数 | C21: =COUNTIF('指标树'!B3:B337,"指标")+COUNTIF('指标树'!B3:B337,"比率")
B22: 拆解分组数 | C22: =COUNTIF('指标树'!B3:B337,"拆解方式")
B23: 校验一致的分组 | C23: =COUNTIF('指标树'!F3:F337,"✓*")
B24: 校验不一致的分组 | C24: =COUNTIF('指标树'!F3:F337,"✗*")
B25: 目录中完全一致的指标 | C25: =COUNTIF('指标树'!K3:K337,"完全一致")
B26: 需确认对应的指标（近似/多个候选） | C26: =COUNTIF('指标树'!K3:K337,"近似，请核对")+COUNTIF('指标树'!K3:K337,"多个候选，请选择")
B27: 目录中未找到的指标 | C27: =COUNTIF('指标树'!K3:K337,"目录中未找到")
B28: 业务已确认的行 | C28: =COUNTA('指标树'!L3:L337)

Sheet 指标树
A1: 缩进表示上下级；点左侧“+/-”可展开、收起。〔 〕为拆解方式；↪ 为引用（该指标的完整拆解在别处，见备注） | B1: 板块 / 指标 / 拆解方式 / 比率 / 引用 | C1: 加：计入上级；减：从上级扣除；其中：属于上级但与其他项交叉，不参与加总 | D1: 来自源报表，仅用于校验 | F1: 在〔拆解方式〕行显示：该组“加/减”下级合计是否等于上级 | G1: 该板块整体情况优先看的指标 | I1: 比率类：分子 ÷ 分母 | J1: 当前问数目录中的候选，多个用“；”分隔 | L1: 请从下拉选择 | M1: 系统发现的疑点已写在这里；业务补充也写在这里 | N1: 系统导入用，与缩进一致；新增节点时请填写 | O1: 系统导入用；新增节点时请填写
A2: 指标树 | B2: 类型 | C2: 加/减/其中 | D2: 参考值 | E2: 单位 | F2: 自动校验 | G2: 核心指标 （建议） | H2: 好坏方向 （建议） | I2: 比率计算 （建议） | J2: 对应目录指标 （系统候选） | K2: 匹配情况 | L2: 业务确认 | M2: 备注 | N2: 上级指标 | O2: 拆解方式 | P2: 数值来源
A3: 一、规模与资本 | B3: 板块
A4: 总资产 | B4: 指标 | D4: 54379.99 | E4: 亿元 | G4: 是 | H4: 越大越好 | K4: 目录中未找到 | P4: 一览表 2026年7月末（全省，亿元/万户）
A5: 核心一级资本净额 | B5: 指标 | D5: 季度指标 | E5: 亿元 | H5: 越大越好 | K5: 目录中未找到 | M5: 季度指标 | P5: 一览表 2026年7月末（全省，亿元/万户）
A6: 核心一级资本充足率 | B6: 比率 | D6: 季度指标 | E6: % | H6: 越大越好 | I6: 核心一级资本净额 ÷ 风险加权资产 | K6: 目录中未找到 | M6: 季度指标 | N6: 核心一级资本净额 | O6: 比率 | P6: 一览表
A7: 一级资本净额 | B7: 指标 | D7: 季度指标 | E7: 亿元 | H7: 越大越好 | K7: 目录中未找到 | M7: 季度指标 | P7: 一览表 2026年7月末（全省，亿元/万户）
A8: 一级资本充足率 | B8: 比率 | D8: 季度指标 | E8: % | H8: 越大越好 | I8: 一级资本净额 ÷ 风险加权资产 | K8: 目录中未找到 | M8: 季度指标 | N8: 一级资本净额 | O8: 比率 | P8: 一览表
A9: 资本净额 | B9: 指标 | D9: 季度指标 | E9: 亿元 | H9: 越大越好 | K9: 目录中未找到 | M9: 季度指标 | P9: 一览表 2026年7月末（全省，亿元/万户）
A10: 资本充足率 | B10: 比率 | D10: 季度指标 | E10: % | H10: 越大越好 | I10: 资本净额 ÷ 风险加权资产 | J10: 资本充足比率 | K10: 完全一致 | M10: 季度指标 | N10: 资本净额 | O10: 比率 | P10: 一览表
A11: 风险加权资产 | B11: 指标 | D11: 季度指标 | E11: 亿元 | H11: 无明显好坏 | K11: 目录中未找到 | M11: 季度指标 | P11: 一览表 2026年7月末（全省，亿元/万户）
A12: 二、存款 | B12: 板块
A13: 各项存款 | B13: 指标 | D13: 44389.53 | E13: 亿元 | G13: 是 | H13: 越大越好 | J13: 各项存款余额 | K13: 完全一致 | P13: 一览表 2026年7月末（全省，亿元/万户）
A14: 〔按客户类型〕 | B14: 拆解方式 | F14: =IF((COUNTIFS($N$3:$N$337,N14,$O$3:$O$337,O14,$C$3:$C$337,"加")+COUNTIFS($N$3:$N$337,N14,$O$3:$O$337,O14,$C$3:$C$337,"减"))=0,"其中项，不参与加总",IF(ISNUMBER(D13)=FALSE,"上级无数值，无法校验",IF(SUMPRODUCT(($N$3:$N$337=N14)*($O$3:$O$337=O14)*(($C$3:$C$337="加")+($C$3:$C$337="减"))*(ISNUMBER($D$3:$D$337)=FALSE))>0,"部分下级无数值，无法校验",IF(ABS(D13-(SUMIFS($D$3:$D$337,$N$3:$N$337,N14,$O$3:$O$337,O14,$C$3:$C$337,"加")-SUMIFS($D$3:$D$337,$N$3:$N$337,N14,$O$3:$O$337,O14,$C$3:$C$337,"减")))<=MAX(0.05,ABS(D13)*0.0005),"✓ 合计与上级一致","✗ 合计与上级相差 "&TEXT(D13-(SUMIFS($D$3:$D$337,$N$3:$N$337,N14,$O$3:$O$337,O14,$C$3:$C$337,"加")-SUMIFS($D$3:$D$337,$N$3:$N$337,N14,$O$3:$O$337,O14,$C$3:$C$337,"减")),"#,##0.00"))))) | N14: 各项存款 | O14: 按客户类型
A15: 个人存款 | B15: 指标 | C15: 加 | D15: 33238.53 | E15: 亿元 | G15: 是 | H15: 越大越好 | J15: 个人存款余额 | K15: 完全一致 | N15: 各项存款 | O15: 按客户类型 | P15: 一览表 2026年7月末（全省，亿元/万户）
A16: 个人存款占比 | B16: 比率 | D16: 0.75 | E16: % | H16: 无明显好坏 | I16: 个人存款 ÷ 各项存款 | J16: 个人存款余额占比 | K16: 近似，请核对 | N16: 个人存款 | O16: 比率 | P16: 一览表
A17: 〔按存款类型〕 | B17: 拆解方式 | F17: =IF((COUNTIFS($N$3:$N$337,N17,$O$3:$O$337,O17,$C$3:$C$337,"加")+COUNTIFS($N$3:$N$337,N17,$O$3:$O$337,O17,$C$3:$C$337,"减"))=0,"其中项，不参与加总",IF(ISNUMBER(D15)=FALSE,"上级无数值，无法校验",IF(SUMPRODUCT(($N$3:$N$337=N17)*($O$3:$O$337=O17)*(($C$3:$C$337="加")+($C$3:$C$337="减"))*(ISNUMBER($D$3:$D$337)=FALSE))>0,"部分下级无数值，无法校验",IF(ABS(D15-(SUMIFS($D$3:$D$337,$N$3:$N$337,N17,$O$3:$O$337,O17,$C$3:$C$337,"加")-SUMIFS($D$3:$D$337,$N$3:$N$337,N17,$O$3:$O$337,O17,$C$3:$C$337,"减")))<=MAX(0.05,ABS(D15)*0.0005),"✓ 合计与上级一致","✗ 合计与上级相差 "&TEXT(D15-(SUMIFS($D$3:$D$337,$N$3:$N$337,N17,$O$3:$O$337,O17,$C$3:$C$337,"加")-SUMIFS($D$3:$D$337,$N$3:$N$337,N17,$O$3:$O$337,O17,$C$3:$C$337,"减")),"#,##0.00"))))) | N17: 个人存款 | O17: 按存款类型
A18: 个人活期存款 | B18: 指标 | C18: 加 | D18: 4647.38 | E18: 亿元 | H18: 越大越好 | J18: 个人活期存款余额 | K18: 完全一致 | N18: 个人存款 | O18: 按存款类型 | P18: 一览表 2026年7月末（全省，亿元/万户）
A19: 个人活期存款占个人存款比 | B19: 比率 | D19: 0.14 | E19: % | H19: 无明显好坏 | I19: 个人活期存款 ÷ 个人存款 | J19: 个人活期存款余额占比 | K19: 近似，请核对 | N19: 个人活期存款 | O19: 比率 | P19: 一览表
A20: 个人定期存款 | B20: 指标 | C20: 加 | D20: 28591.15 | E20: 亿元 | H20: 越大越好 | J20: 个人定期存款余额 | K20: 完全一致 | N20: 个人存款 | O20: 按存款类型 | P20: 一览表 2026年7月末（全省，亿元/万户）
A21: 个人定期存款占个人存款比 | B21: 比率 | D21: 0.86 | E21: % | H21: 无明显好坏 | I21: 个人定期存款 ÷ 个人存款 | K21: 目录中未找到 | N21: 个人定期存款 | O21: 比率 | P21: 一览表
A22: 〔按存款期限〕 | B22: 拆解方式 | F22: =IF((COUNTIFS($N$3:$N$337,N22,$O$3:$O$337,O22,$C$3:$C$337,"加")+COUNTIFS($N$3:$N$337,N22,$O$3:$O$337,O22,$C$3:$C$337,"减"))=0,"其中项，不参与加总",IF(ISNUMBER(D20)=FALSE,"上级无数值，无法校验",IF(SUMPRODUCT(($N$3:$N$337=N22)*($O$3:$O$337=O22)*(($C$3:$C$337="加")+($C$3:$C$337="减"))*(ISNUMBER($D$3:$D$337)=FALSE))>0,"部分下级无数值，无法校验",IF(ABS(D20-(SUMIFS($D$3:$D$337,$N$3:$N$337,N22,$O$3:$O$337,O22,$C$3:$C$337,"加")-SUMIFS($D$3:$D$337,$N$3:$N$337,N22,$O$3:$O$337,O22,$C$3:$C$337,"减")))<=MAX(0.05,ABS(D20)*0.0005),"✓ 合计与上级一致","✗ 合计与上级相差 "&TEXT(D20-(SUMIFS($D$3:$D$337,$N$3:$N$337,N22,$O$3:$O$337,O22,$C$3:$C$337,"加")-SUMIFS($D$3:$D$337,$N$3:$N$337,N22,$O$3:$O$337,O22,$C$3:$C$337,"减")),"#,##0.00"))))) | M22: 报表只列了四个期限，合计与个人定期存款不相等，可能还有其他期限，请业务补充或确认 | N22: 个人定期存款 | O22: 按存款期限
A23: 个人定期存款-一年期及以下 | B23: 指标 | C23: 加 | D23: 7335.94 | E23: 亿元 | H23: 越大越好 | K23: 目录中未找到 | N23: 个人定期存款 | O23: 按存款期限 | P23: 一览表 2026年7月末（全省，亿元/万户）
A24: 一年期及以下占个人定期比 | B24: 比率 | D24: 0.26 | E24: % | H24: 无明显好坏 | I24: 个人定期存款-一年期及以下 ÷ 个人定期存款 | K24: 目录中未找到 | N24: 个人定期存款-一年期及以下 | O24: 比率 | P24: 一览表
A25: 个人定期存款-二年期 | B25: 指标 | C25: 加 | D25: 3611.3 | E25: 亿元 | H25: 越大越好 | J25: 个人两年定期存款余额 | K25: 近似，请核对 | N25: 个人定期存款 | O25: 按存款期限 | P25: 一览表 2026年7月末（全省，亿元/万户）
A26: 二年期占个人定期比 | B26: 比率 | D26: 0.13 | E26: % | H26: 无明显好坏 | I26: 个人定期存款-二年期 ÷ 个人定期存款 | K26: 目录中未找到 | N26: 个人定期存款-二年期 | O26: 比率 | P26: 一览表
A27: 个人定期存款-三年期 | B27: 指标 | C27: 加 | D27: 15018.54 | E27: 亿元 | H27: 越大越好 | J27: 个人三年定期存款余额 | K27: 近似，请核对 | N27: 个人定期存款 | O27: 按存款期限 | P27: 一览表 2026年7月末（全省，亿元/万户）
A28: 三年期占个人定期比 | B28: 比率 | D28: 0.53 | E28: % | H28: 无明显好坏 | I28: 个人定期存款-三年期 ÷ 个人定期存款 | K28: 目录中未找到 | N28: 个人定期存款-三年期 | O28: 比率 | P28: 一览表
A29: 个人定期存款-五年期 | B29: 指标 | C29: 加 | D29: 473.53 | E29: 亿元 | H29: 越大越好 | K29: 目录中未找到 | N29: 个人定期存款 | O29: 按存款期限 | P29: 一览表 2026年7月末（全省，亿元/万户）
A30: 五年期占个人定期比 | B30: 比率 | D30: 0.02 | E30: % | H30: 无明显好坏 | I30: 个人定期存款-五年期 ÷ 个人定期存款 | K30: 目录中未找到 | N30: 个人定期存款-五年期 | O30: 比率 | P30: 一览表
A31: 对公存款 | B31: 指标 | C31: 加 | D31: 11151 | E31: 亿元 | G31: 是 | H31: 越大越好 | J31: 对公存款余额 | K31: 完全一致 | N31: 各项存款 | O31: 按客户类型 | P31: 一览表 2026年7月末（全省，亿元/万户）
A32: 对公存款占比 | B32: 比率 | D32: 0.25 | E32: % | H32: 无明显好坏 | I32: 对公存款 ÷ 各项存款 | J32: 对公存款余额占比 | K32: 近似，请核对 | N32: 对公存款 | O32: 比率 | P32: 一览表
A33: 〔按存款类型〕 | B33: 拆解方式 | F33: =IF((COUNTIFS($N$3:$N$337,N33,$O$3:$O$337,O33,$C$3:$C$337,"加")+COUNTIFS($N$3:$N$337,N33,$O$3:$O$337,O33,$C$3:$C$337,"减"))=0,"其中项，不参与加总",IF(ISNUMBER(D31)=FALSE,"上级无数值，无法校验",IF(SUMPRODUCT(($N$3:$N$337=N33)*($O$3:$O$337=O33)*(($C$3:$C$337="加")+($C$3:$C$337="减"))*(ISNUMBER($D$3:$D$337)=FALSE))>0,"部分下级无数值，无法校验",IF(ABS(D31-(SUMIFS($D$3:$D$337,$N$3:$N$337,N33,$O$3:$O$337,O33,$C$3:$C$337,"加")-SUMIFS($D$3:$D$337,$N$3:$N$337,N33,$O$3:$O$337,O33,$C$3:$C$337,"减")))<=MAX(0.05,ABS(D31)*0.0005),"✓ 合计与上级一致","✗ 合计与上级相差 "&TEXT(D31-(SUMIFS($D$3:$D$337,$N$3:$N$337,N33,$O$3:$O$337,O33,$C$3:$C$337,"加")-SUMIFS($D$3:$D$337,$N$3:$N$337,N33,$O$3:$O$337,O33,$C$3:$C$337,"减")),"#,##0.00"))))) | N33: 对公存款 | O33: 按存款类型
A34: 对公活期存款 | B34: 指标 | C34: 加 | D34: 3669.21 | E34: 亿元 | H34: 越大越好 | J34: 对公活期存款余额 | K34: 完全一致 | N34: 对公存款 | O34: 按存款类型 | P34: 一览表 2026年7月末（全省，亿元/万户）
A35: 对公活期存款占对公存款比 | B35: 比率 | D35: 0.33 | E35: % | H35: 无明显好坏 | I35: 对公活期存款 ÷ 对公存款 | J35: 对公活期存款余额占比 | K35: 近似，请核对 | N35: 对公活期存款 | O35: 比率 | P35: 一览表
A36: 对公定期存款 | B36: 指标 | C36: 加 | D36: 7481.79 | E36: 亿元 | H36: 越大越好 | J36: 对公定期存款余额 | K36: 完全一致 | N36: 对公存款 | O36: 按存款类型 | P36: 一览表 2026年7月末（全省，亿元/万户）
A37: 对公定期存款占对公存款比 | B37: 比率 | D37: 0.67 | E37: % | H37: 无明显好坏 | I37: 对公定期存款 ÷ 对公存款 | K37: 目录中未找到 | N37: 对公定期存款 | O37: 比率 | P37: 一览表
A38: 〔其中项〕 | B38: 拆解方式 | F38: =IF((COUNTIFS($N$3:$N$337,N38,$O$3:$O$337,O38,$C$3:$C$337,"加")+COUNTIFS($N$3:$N$337,N38,$O$3:$O$337,O38,$C$3:$C$337,"减"))=0,"其中项，不参与加总",IF(ISNUMBER(D31)=FALSE,"上级无数值，无法校验",IF(SUMPRODUCT(($N$3:$N$337=N38)*($O$3:$O$337=O38)*(($C$3:$C$337="加")+($C$3:$C$337="减"))*(ISNUMBER($D$3:$D$337)=FALSE))>0,"部分下级无数值，无法校验",IF(ABS(D31-(SUMIFS($D$3:$D$337,$N$3:$N$337,N38,$O$3:$O$337,O38,$C$3:$C$337,"加")-SUMIFS($D$3:$D$337,$N$3:$N$337,N38,$O$3:$O$337,O38,$C$3:$C$337,"减")))<=MAX(0.05,ABS(D31)*0.0005),"✓ 合计与上级一致","✗ 合计与上级相差 "&TEXT(D31-(SUMIFS($D$3:$D$337,$N$3:$N$337,N38,$O$3:$O$337,O38,$C$3:$C$337,"加")-SUMIFS($D$3:$D$337,$N$3:$N$337,N38,$O$3:$O$337,O38,$C$3:$C$337,"减")),"#,##0.00"))))) | M38: 报表以“其中”列示，与活期/定期有交叉，不参与加总 | N38: 对公存款 | O38: 其中项
A39: 保证金存款 | B39: 指标 | C39: 其中 | D39: 1774.99 | E39: 亿元 | H39: 无明显好坏 | J39: 对公保证金存款余额 | K39: 近似，请核对 | N39: 对公存款 | O39: 其中项 | P39: 一览表 2026年7月末（全省，亿元/万户）
A40: 保证金存款占对公存款比 | B40: 比率 | D40: 0.16 | E40: % | H40: 无明显好坏 | I40: 保证金存款 ÷ 对公存款 | K40: 目录中未找到 | N40: 保证金存款 | O40: 比率 | P40: 一览表
A41: 非银存款 | B41: 指标 | C41: 其中 | D41: 488.34 | E41: 亿元 | H41: 无明显好坏 | K41: 目录中未找到 | N41: 对公存款 | O41: 其中项 | P41: 一览表 2026年7月末（全省，亿元/万户）
A42: 非银存款占对公存款比 | B42: 比率 | D42: 0.04 | E42: % | H42: 无明显好坏 | I42: 非银存款 ÷ 对公存款 | K42: 目录中未找到 | N42: 非银存款 | O42: 比率 | P42: 一览表
A43: 存款市场份额 | B43: 指标 | D43: 待公布 | E43: % | H43: 越大越好 | J43: 存款市场份额；存款市场份额比率 | K43: 多个候选，请选择 | M43: 待公布 | P43: 一览表 2026年7月末（全省，亿元/万户）
A44: 全部3年期以上存款占比 | B44: 指标 | D44: 季度指标 | E44: % | H44: 无明显好坏 | J44: 三年期限以上定期存款余额占比 | K44: 近似，请核对 | M44: 季度指标 | P44: 一览表 2026年7月末（全省，亿元/万户）
A45: 活期存款占比（不含协定存款） | B45: 指标 | D45: 0.19 | E45: % | H45: 越大越好 | I45: 计算方式请业务确认 | J45: 活期存款余额占比 | K45: 近似，请核对 | P45: 一览表 2026年7月末（全省，亿元/万户）
A46: 活期存款占比（含协定存款） | B46: 指标 | D46: 0.22 | E46: % | H46: 越大越好 | I46: 计算方式请业务确认 | J46: 活期存款余额占比 | K46: 近似，请核对 | P46: 一览表 2026年7月末（全省，亿元/万户）
A47: 三、贷款 | B47: 板块
A48: 各项贷款 | B48: 指标 | D48: 35030.41 | E48: 亿元 | G48: 是 | H48: 越大越好 | J48: 各项贷款余额_人行口径；各项贷款余额_剔除贴现及买断式转贴现；各项贷款余额_银监 | K48: 多个候选，请选择 | P48: 一览表 2026年7月末（全省，亿元/万户）
A49: 〔按业务类型〕 | B49: 拆解方式 | F49: =IF((COUNTIFS($N$3:$N$337,N49,$O$3:$O$337,O49,$C$3:$C$337,"加")+COUNTIFS($N$3:$N$337,N49,$O$3:$O$337,O49,$C$3:$C$337,"减"))=0,"其中项，不参与加总",IF(ISNUMBER(D48)=FALSE,"上级无数值，无法校验",IF(SUMPRODUCT(($N$3:$N$337=N49)*($O$3:$O$337=O49)*(($C$3:$C$337="加")+($C$3:$C$337="减"))*(ISNUMBER($D$3:$D$337)=FALSE))>0,"部分下级无数值，无法校验",IF(ABS(D48-(SUMIFS($D$3:$D$337,$N$3:$N$337,N49,$O$3:$O$337,O49,$C$3:$C$337,"加")-SUMIFS($D$3:$D$337,$N$3:$N$337,N49,$O$3:$O$337,O49,$C$3:$C$337,"减")))<=MAX(0.05,ABS(D48)*0.0005),"✓ 合计与上级一致","✗ 合计与上级相差 "&TEXT(D48-(SUMIFS($D$3:$D$337,$N$3:$N$337,N49,$O$3:$O$337,O49,$C$3:$C$337,"加")-SUMIFS($D$3:$D$337,$N$3:$N$337,N49,$O$3:$O$337,O49,$C$3:$C$337,"减")),"#,##0.00"))))) | N49: 各项贷款 | O49: 按业务类型
A50: 个人贷款 | B50: 指标 | C50: 加 | D50: 10571.39 | E50: 亿元 | G50: 是 | H50: 越大越好 | J50: 个人贷款余额 | K50: 完全一致 | N50: 各项贷款 | O50: 按业务类型 | P50: 一览表 2026年7月末（全省，亿元/万户）
A51: 个人贷款占比 | B51: 比率 | D51: 0.3 | E51: % | H51: 无明显好坏 | I51: 个人贷款 ÷ 各项贷款 | J51: 个人贷款余额占比 | K51: 近似，请核对 | N51: 个人贷款 | O51: 比率 | P51: 一览表
A52: 〔按贷款用途〕 | B52: 拆解方式 | F52: =IF((COUNTIFS($N$3:$N$337,N52,$O$3:$O$337,O52,$C$3:$C$337,"加")+COUNTIFS($N$3:$N$337,N52,$O$3:$O$337,O52,$C$3:$C$337,"减"))=0,"其中项，不参与加总",IF(ISNUMBER(D50)=FALSE,"上级无数值，无法校验",IF(SUMPRODUCT(($N$3:$N$337=N52)*($O$3:$O$337=O52)*(($C$3:$C$337="加")+($C$3:$C$337="减"))*(ISNUMBER($D$3:$D$337)=FALSE))>0,"部分下级无数值，无法校验",IF(ABS(D50-(SUMIFS($D$3:$D$337,$N$3:$N$337,N52,$O$3:$O$337,O52,$C$3:$C$337,"加")-SUMIFS($D$3:$D$337,$N$3:$N$337,N52,$O$3:$O$337,O52,$C$3:$C$337,"减")))<=MAX(0.05,ABS(D50)*0.0005),"✓ 合计与上级一致","✗ 合计与上级相差 "&TEXT(D50-(SUMIFS($D$3:$D$337,$N$3:$N$337,N52,$O$3:$O$337,O52,$C$3:$C$337,"加")-SUMIFS($D$3:$D$337,$N$3:$N$337,N52,$O$3:$O$337,O52,$C$3:$C$337,"减")),"#,##0.00"))))) | N52: 个人贷款 | O52: 按贷款用途
A53: 个人经营性贷款 | B53: 指标 | C53: 加 | D53: 6280.91 | E53: 亿元 | H53: 越大越好 | J53: 个人经营性贷款余额 | K53: 完全一致 | N53: 个人贷款 | O53: 按贷款用途 | P53: 一览表 2026年7月末（全省，亿元/万户）
A54: 个人经营性贷款占个人贷款比 | B54: 比率 | D54: 0.59 | E54: % | H54: 无明显好坏 | I54: 个人经营性贷款 ÷ 个人贷款 | K54: 目录中未找到 | N54: 个人经营性贷款 | O54: 比率 | P54: 一览表
A55: 个人一般性消费贷款 | B55: 指标 | C55: 加 | D55: 1850.76 | E55: 亿元 | H55: 越大越好 | J55: 个人消费贷款余额 | K55: 近似，请核对 | N55: 个人贷款 | O55: 按贷款用途 | P55: 一览表 2026年7月末（全省，亿元/万户）
A56: 个人一般性消费贷款占个人贷款比 | B56: 比率 | D56: 0.18 | E56: % | H56: 无明显好坏 | I56: 个人一般性消费贷款 ÷ 个人贷款 | K56: 目录中未找到 | N56: 个人一般性消费贷款 | O56: 比率 | P56: 一览表
A57: 个人住房按揭贷款 | B57: 指标 | C57: 加 | D57: 2304.72 | E57: 亿元 | H57: 越大越好 | K57: 目录中未找到 | N57: 个人贷款 | O57: 按贷款用途 | P57: 一览表 2026年7月末（全省，亿元/万户）
A58: 个人住房按揭贷款占个人贷款比 | B58: 比率 | D58: 0.22 | E58: % | H58: 无明显好坏 | I58: 个人住房按揭贷款 ÷ 个人贷款 | K58: 目录中未找到 | N58: 个人住房按揭贷款 | O58: 比率 | P58: 一览表
A59: 个人信用卡透支及分期 | B59: 指标 | C59: 加 | D59: 135.01 | E59: 亿元 | H59: 越大越好 | K59: 目录中未找到 | N59: 个人贷款 | O59: 按贷款用途 | P59: 一览表 2026年7月末（全省，亿元/万户）
A60: 个人信用卡透支占个人贷款比 | B60: 比率 | D60: 0.01 | E60: % | H60: 无明显好坏 | I60: 个人信用卡透支及分期 ÷ 个人贷款 | K60: 目录中未找到 | N60: 个人信用卡透支及分期 | O60: 比率 | P60: 一览表
A61: 〔按借款主体〕 | B61: 拆解方式 | F61: =IF((COUNTIFS($N$3:$N$337,N61,$O$3:$O$337,O61,$C$3:$C$337,"加")+COUNTIFS($N$3:$N$337,N61,$O$3:$O$337,O61,$C$3:$C$337,"减"))=0,"其中项，不参与加总",IF(ISNUMBER(D50)=FALSE,"上级无数值，无法校验",IF(SUMPRODUCT(($N$3:$N$337=N61)*($O$3:$O$337=O61)*(($C$3:$C$337="加")+($C$3:$C$337="减"))*(ISNUMBER($D$3:$D$337)=FALSE))>0,"部分下级无数值，无法校验",IF(ABS(D50-(SUMIFS($D$3:$D$337,$N$3:$N$337,N61,$O$3:$O$337,O61,$C$3:$C$337,"加")-SUMIFS($D$3:$D$337,$N$3:$N$337,N61,$O$3:$O$337,O61,$C$3:$C$337,"减")))<=MAX(0.05,ABS(D50)*0.0005),"✓ 合计与上级一致","✗ 合计与上级相差 "&TEXT(D50-(SUMIFS($D$3:$D$337,$N$3:$N$337,N61,$O$3:$O$337,O61,$C$3:$C$337,"加")-SUMIFS($D$3:$D$337,$N$3:$N$337,N61,$O$3:$O$337,O61,$C$3:$C$337,"减")),"#,##0.00"))))) | M61: 报表只列了两类主体，不构成完整拆分 | N61: 个人贷款 | O61: 按借款主体
A62: 农户贷款 | B62: 指标 | C62: 其中 | D62: 季度指标 | E62: 亿元 | H62: 越大越好 | K62: 目录中未找到 | M62: 季度指标 | N62: 个人贷款 | O62: 按借款主体 | P62: 一览表 2026年7月末（全省，亿元/万户）
A63: 农户贷款占个人贷款比 | B63: 比率 | D63: 季度指标 | E63: % | H63: 无明显好坏 | I63: 农户贷款 ÷ 个人贷款 | K63: 目录中未找到 | M63: 季度指标 | N63: 农户贷款 | O63: 比率 | P63: 一览表
A64: 个体工商户贷款 | B64: 指标 | C64: 其中 | D64: 2661.05 | E64: 亿元 | H64: 越大越好 | K64: 目录中未找到 | N64: 个人贷款 | O64: 按借款主体 | P64: 一览表 2026年7月末（全省，亿元/万户）
A65: 个体工商户贷款占个人贷款比 | B65: 比率 | D65: 0.25 | E65: % | H65: 无明显好坏 | I65: 个体工商户贷款 ÷ 个人贷款 | K65: 目录中未找到 | N65: 个体工商户贷款 | O65: 比率 | P65: 一览表
A66: 对公贷款（剔除贴现） | B66: 指标 | C66: 加 | D66: 20109.92 | E66: 亿元 | G66: 是 | H66: 越大越好 | J66: 对公贷款余额_不含贴现及买断式转贴现 | K66: 近似，请核对 | N66: 各项贷款 | O66: 按业务类型 | P66: 一览表 2026年7月末（全省，亿元/万户）
A67: 对公贷款占比 | B67: 比率 | D67: 0.57 | E67: % | H67: 无明显好坏 | I67: 对公贷款（剔除贴现） ÷ 各项贷款 | K67: 目录中未找到 | N67: 对公贷款（剔除贴现） | O67: 比率 | P67: 一览表
A68: 〔按担保方式〕 | B68: 拆解方式 | F68: =IF((COUNTIFS($N$3:$N$337,N68,$O$3:$O$337,O68,$C$3:$C$337,"加")+COUNTIFS($N$3:$N$337,N68,$O$3:$O$337,O68,$C$3:$C$337,"减"))=0,"其中项，不参与加总",IF(ISNUMBER(D66)=FALSE,"上级无数值，无法校验",IF(SUMPRODUCT(($N$3:$N$337=N68)*($O$3:$O$337=O68)*(($C$3:$C$337="加")+($C$3:$C$337="减"))*(ISNUMBER($D$3:$D$337)=FALSE))>0,"部分下级无数值，无法校验",IF(ABS(D66-(SUMIFS($D$3:$D$337,$N$3:$N$337,N68,$O$3:$O$337,O68,$C$3:$C$337,"加")-SUMIFS($D$3:$D$337,$N$3:$N$337,N68,$O$3:$O$337,O68,$C$3:$C$337,"减")))<=MAX(0.05,ABS(D66)*0.0005),"✓ 合计与上级一致","✗ 合计与上级相差 "&TEXT(D66-(SUMIFS($D$3:$D$337,$N$3:$N$337,N68,$O$3:$O$337,O68,$C$3:$C$337,"加")-SUMIFS($D$3:$D$337,$N$3:$N$337,N68,$O$3:$O$337,O68,$C$3:$C$337,"减")),"#,##0.00"))))) | N68: 对公贷款（剔除贴现） | O68: 按担保方式
A69: 对公信用贷款 | B69: 指标 | C69: 加 | D69: 3219.57 | E69: 亿元 | H69: 越大越好 | K69: 目录中未找到 | N69: 对公贷款（剔除贴现） | O69: 按担保方式 | P69: 一览表 2026年7月末（全省，亿元/万户）
A70: 对公信用贷款占对公贷款比 | B70: 比率 | D70: 0.16 | E70: % | H70: 无明显好坏 | I70: 对公信用贷款 ÷ 对公贷款（剔除贴现） | K70: 目录中未找到 | N70: 对公信用贷款 | O70: 比率 | P70: 一览表
A71: 对公保证贷款 | B71: 指标 | C71: 加 | D71: 10306.53 | E71: 亿元 | H71: 无明显好坏 | K71: 目录中未找到 | N71: 对公贷款（剔除贴现） | O71: 按担保方式 | P71: 一览表 2026年7月末（全省，亿元/万户）
A72: 对公保证贷款占对公贷款比 | B72: 比率 | D72: 0.51 | E72: % | H72: 无明显好坏 | I72: 对公保证贷款 ÷ 对公贷款（剔除贴现） | K72: 目录中未找到 | N72: 对公保证贷款 | O72: 比率 | P72: 一览表
A73: 对公抵质押贷款 | B73: 指标 | C73: 加 | D73: 6583.8 | E73: 亿元 | H73: 越大越好 | K73: 目录中未找到 | N73: 对公贷款（剔除贴现） | O73: 按担保方式 | P73: 一览表 2026年7月末（全省，亿元/万户）
A74: 对公抵质押贷款占对公贷款比 | B74: 比率 | D74: 0.33 | E74: % | H74: 无明显好坏 | I74: 对公抵质押贷款 ÷ 对公贷款（剔除贴现） | K74: 目录中未找到 | N74: 对公抵质押贷款 | O74: 比率 | P74: 一览表
A75: 〔按企业性质〕 | B75: 拆解方式 | F75: =IF((COUNTIFS($N$3:$N$337,N75,$O$3:$O$337,O75,$C$3:$C$337,"加")+COUNTIFS($N$3:$N$337,N75,$O$3:$O$337,O75,$C$3:$C$337,"减"))=0,"其中项，不参与加总",IF(ISNUMBER(D66)=FALSE,"上级无数值，无法校验",IF(SUMPRODUCT(($N$3:$N$337=N75)*($O$3:$O$337=O75)*(($C$3:$C$337="加")+($C$3:$C$337="减"))*(ISNUMBER($D$3:$D$337)=FALSE))>0,"部分下级无数值，无法校验",IF(ABS(D66-(SUMIFS($D$3:$D$337,$N$3:$N$337,N75,$O$3:$O$337,O75,$C$3:$C$337,"加")-SUMIFS($D$3:$D$337,$N$3:$N$337,N75,$O$3:$O$337,O75,$C$3:$C$337,"减")))<=MAX(0.05,ABS(D66)*0.0005),"✓ 合计与上级一致","✗ 合计与上级相差 "&TEXT(D66-(SUMIFS($D$3:$D$337,$N$3:$N$337,N75,$O$3:$O$337,O75,$C$3:$C$337,"加")-SUMIFS($D$3:$D$337,$N$3:$N$337,N75,$O$3:$O$337,O75,$C$3:$C$337,"减")),"#,##0.00"))))) | M75: 国企+私企与对公贷款不相等，报表中两者占比的分母为各项贷款，请确认 | N75: 对公贷款（剔除贴现） | O75: 按企业性质
A76: 国企贷款 | B76: 指标 | C76: 其中 | D76: 8298.83 | E76: 亿元 | H76: 越大越好 | K76: 目录中未找到 | N76: 对公贷款（剔除贴现） | O76: 按企业性质 | P76: 一览表 2026年7月末（全省，亿元/万户）
A77: 国企贷款占各项贷款比 | B77: 比率 | D77: 0.24 | E77: % | H77: 无明显好坏 | I77: 国企贷款 ÷ 各项贷款 | K77: 目录中未找到 | N77: 国企贷款 | O77: 比率 | P77: 一览表
A78: 私企贷款 | B78: 指标 | C78: 其中 | D78: 10343.26 | E78: 亿元 | H78: 越大越好 | K78: 目录中未找到 | N78: 对公贷款（剔除贴现） | O78: 按企业性质 | P78: 一览表 2026年7月末（全省，亿元/万户）
A79: 私企贷款占各项贷款比 | B79: 比率 | D79: 0.3 | E79: % | H79: 无明显好坏 | I79: 私企贷款 ÷ 各项贷款 | K79: 目录中未找到 | N79: 私企贷款 | O79: 比率 | P79: 一览表
A80: 贴现及买断式转贴现 | B80: 指标 | C80: 加 | D80: 4349.1 | E80: 亿元 | H80: 无明显好坏 | J80: 贴现及买断式转贴现余额 | K80: 完全一致 | N80: 各项贷款 | O80: 按业务类型 | P80: 一览表 2026年7月末（全省，亿元/万户）
A81: 贴现资产占各项贷款比 | B81: 比率 | D81: 0.13 | E81: % | H81: 无明显好坏 | I81: 贴现及买断式转贴现 ÷ 各项贷款 | J81: 贴现及买断式转贴现余额占比 | K81: 近似，请核对 | N81: 贴现及买断式转贴现 | O81: 比率 | P81: 一览表
A82: 〔按贴现类型〕 | B82: 拆解方式 | F82: =IF((COUNTIFS($N$3:$N$337,N82,$O$3:$O$337,O82,$C$3:$C$337,"加")+COUNTIFS($N$3:$N$337,N82,$O$3:$O$337,O82,$C$3:$C$337,"减"))=0,"其中项，不参与加总",IF(ISNUMBER(D80)=FALSE,"上级无数值，无法校验",IF(SUMPRODUCT(($N$3:$N$337=N82)*($O$3:$O$337=O82)*(($C$3:$C$337="加")+($C$3:$C$337="减"))*(ISNUMBER($D$3:$D$337)=FALSE))>0,"部分下级无数值，无法校验",IF(ABS(D80-(SUMIFS($D$3:$D$337,$N$3:$N$337,N82,$O$3:$O$337,O82,$C$3:$C$337,"加")-SUMIFS($D$3:$D$337,$N$3:$N$337,N82,$O$3:$O$337,O82,$C$3:$C$337,"减")))<=MAX(0.05,ABS(D80)*0.0005),"✓ 合计与上级一致","✗ 合计与上级相差 "&TEXT(D80-(SUMIFS($D$3:$D$337,$N$3:$N$337,N82,$O$3:$O$337,O82,$C$3:$C$337,"加")-SUMIFS($D$3:$D$337,$N$3:$N$337,N82,$O$3:$O$337,O82,$C$3:$C$337,"减")),"#,##0.00"))))) | N82: 贴现及买断式转贴现 | O82: 按贴现类型
A83: 直贴 | B83: 指标 | C83: 加 | D83: 2349.48 | E83: 亿元 | H83: 无明显好坏 | J83: 贴现余额 | K83: 近似，请核对 | N83: 贴现及买断式转贴现 | O83: 按贴现类型 | P83: 一览表 2026年7月末（全省，亿元/万户）
A84: 直贴占全部贴现资产比重 | B84: 比率 | D84: 0.54 | E84: % | H84: 无明显好坏 | I84: 直贴 ÷ 贴现及买断式转贴现 | K84: 目录中未找到 | N84: 直贴 | O84: 比率 | P84: 一览表
A85: 买断式转贴现 | B85: 指标 | C85: 加 | D85: 1999.62 | E85: 亿元 | H85: 无明显好坏 | J85: 买断式转贴现余额 | K85: 完全一致 | N85: 贴现及买断式转贴现 | O85: 按贴现类型 | P85: 一览表 2026年7月末（全省，亿元/万户）
A86: 买断式转贴现占全部贴现资产比重 | B86: 比率 | D86: 0.46 | E86: % | H86: 无明显好坏 | I86: 买断式转贴现 ÷ 贴现及买断式转贴现 | K86: 目录中未找到 | N86: 买断式转贴现 | O86: 比率 | P86: 一览表
A87: 〔专项口径〕 | B87: 拆解方式 | F87: =IF((COUNTIFS($N$3:$N$337,N87,$O$3:$O$337,O87,$C$3:$C$337,"加")+COUNTIFS($N$3:$N$337,N87,$O$3:$O$337,O87,$C$3:$C$337,"减"))=0,"其中项，不参与加总",IF(ISNUMBER(D48)=FALSE,"上级无数值，无法校验",IF(SUMPRODUCT(($N$3:$N$337=N87)*($O$3:$O$337=O87)*(($C$3:$C$337="加")+($C$3:$C$337="减"))*(ISNUMBER($D$3:$D$337)=FALSE))>0,"部分下级无数值，无法校验",IF(ABS(D48-(SUMIFS($D$3:$D$337,$N$3:$N$337,N87,$O$3:$O$337,O87,$C$3:$C$337,"加")-SUMIFS($D$3:$D$337,$N$3:$N$337,N87,$O$3:$O$337,O87,$C$3:$C$337,"减")))<=MAX(0.05,ABS(D48)*0.0005),"✓ 合计与上级一致","✗ 合计与上级相差 "&TEXT(D48-(SUMIFS($D$3:$D$337,$N$3:$N$337,N87,$O$3:$O$337,O87,$C$3:$C$337,"加")-SUMIFS($D$3:$D$337,$N$3:$N$337,N87,$O$3:$O$337,O87,$C$3:$C$337,"减")),"#,##0.00"))))) | M87: 专项口径之间相互交叉，不参与加总 | N87: 各项贷款 | O87: 专项口径
A88: ↪ 涉农贷款 | B88: 引用 | C88: 其中 | D88: 12917.43 | E88: 亿元 | M88: 展开见：涉农贷款 | N88: 各项贷款 | O88: 专项口径 | P88: 一览表 2026年7月末（全省，亿元/万户）
A89: ↪ 小微企业贷款（不含转贴现） | B89: 引用 | C89: 其中 | D89: 22936.01 | E89: 亿元 | M89: 展开见：小微企业贷款（不含转贴现） | N89: 各项贷款 | O89: 专项口径 | P89: 一览表 2026年7月末（全省，亿元/万户）
A90: ↪ 涉农与小微企业贷款 | B90: 引用 | C90: 其中 | D90: 27606.07 | E90: 亿元 | M90: 展开见：涉农与小微企业贷款 | N90: 各项贷款 | O90: 专项口径 | P90: 一览表 2026年7月末（全省，亿元/万户）
A91: ↪ 普惠型农户和普惠型小微企业贷款 | B91: 引用 | C91: 其中 | D91: 11798.58 | E91: 亿元 | M91: 展开见：普惠型农户和普惠型小微企业贷款 | N91: 各项贷款 | O91: 专项口径 | P91: 一览表 2026年7月末（全省，亿元/万户）
A92: ↪ 民营企业贷款（全口径） | B92: 引用 | C92: 其中 | D92: 18730.49 | E92: 亿元 | M92: 展开见：民营企业贷款（全口径） | N92: 各项贷款 | O92: 专项口径 | P92: 一览表 2026年7月末（全省，亿元/万户）
A93: ↪ 制造业贷款 | B93: 引用 | C93: 其中 | D93: 8661 | E93: 亿元 | M93: 展开见：制造业贷款 | N93: 各项贷款 | O93: 专项口径 | P93: 一览表 2026年7月末（全省，亿元/万户）
A94: ↪ 服务业贷款 | B94: 引用 | C94: 其中 | D94: 13206.67 | E94: 亿元 | M94: 展开见：服务业贷款 | N94: 各项贷款 | O94: 专项口径 | P94: 一览表 2026年7月末（全省，亿元/万户）
A95: 贷款市场份额 | B95: 指标 | D95: 待公布 | E95: % | H95: 越大越好 | J95: 贷款市场份额；贷款市场份额比率 | K95: 多个候选，请选择 | M95: 待公布 | P95: 一览表 2026年7月末（全省，亿元/万户）
A96: 100万以下贷款占比 | B96: 指标 | D96: 季度指标 | E96: % | H96: 越大越好 | J96: 100万以下贷款占比 | K96: 完全一致 | M96: 季度指标 | P96: 一览表 2026年7月末（全省，亿元/万户）
A97: 3000万以上贷款占比 | B97: 指标 | D97: 季度指标 | E97: % | H97: 越小越好 | J97: 三千万元不含以上贷款占比 | K97: 近似，请核对 | M97: 季度指标 | P97: 一览表 2026年7月末（全省，亿元/万户）
A98: 四、客户 | B98: 板块
A99: 信贷客户数 | B99: 指标 | D99: 397.56 | E99: 万户 | G99: 是 | H99: 越大越好 | J99: 信贷客户数量 | K99: 完全一致 | P99: 一览表 2026年7月末（全省，亿元/万户）
A100: 〔按客户类型〕 | B100: 拆解方式 | F100: =IF((COUNTIFS($N$3:$N$337,N100,$O$3:$O$337,O100,$C$3:$C$337,"加")+COUNTIFS($N$3:$N$337,N100,$O$3:$O$337,O100,$C$3:$C$337,"减"))=0,"其中项，不参与加总",IF(ISNUMBER(D99)=FALSE,"上级无数值，无法校验",IF(SUMPRODUCT(($N$3:$N$337=N100)*($O$3:$O$337=O100)*(($C$3:$C$337="加")+($C$3:$C$337="减"))*(ISNUMBER($D$3:$D$337)=FALSE))>0,"部分下级无数值，无法校验",IF(ABS(D99-(SUMIFS($D$3:$D$337,$N$3:$N$337,N100,$O$3:$O$337,O100,$C$3:$C$337,"加")-SUMIFS($D$3:$D$337,$N$3:$N$337,N100,$O$3:$O$337,O100,$C$3:$C$337,"减")))<=MAX(0.05,ABS(D99)*0.0005),"✓ 合计与上级一致","✗ 合计与上级相差 "&TEXT(D99-(SUMIFS($D$3:$D$337,$N$3:$N$337,N100,$O$3:$O$337,O100,$C$3:$C$337,"加")-SUMIFS($D$3:$D$337,$N$3:$N$337,N100,$O$3:$O$337,O100,$C$3:$C$337,"减")),"#,##0.00"))))) | N100: 信贷客户数 | O100: 按客户类型
...

Sheet 选项
A1: 是 | B1: 越大越好 | C1: 加 | D1: 正确 | E1: 当日数
A2: 否 | B2: 越小越好 | C2: 减 | D2: 有误（备注说明） | E2: 进取类均值
B3: 无明显好坏 | C3: 其中 | D3: 目录中没有 | E3: 较年初
D4: 不需要 | E4: 较年初增幅
E5: 较年初增幅层级排名
E6: 较年初增幅排名
E7: 较年初增量排名
E8: 较上月
E9: 较上月增幅
E10: 较上月增幅排名
E11: 较上月增量排名
E12: 较上季
E13: 较上季增幅
E14: 较上季增幅排名
E15: 较上季增量排名
E16: 较层级均值
... E33: 全省均值
